cogent3_h5seqs/__init__.py
cogent3_h5seqs-0.7.1.dist-info/METADATA
cogent3_h5seqs-0.7.1.dist-info/WHEEL
cogent3_h5seqs-0.7.1.dist-info/entry_points.txt
cogent3_h5seqs-0.7.1.dist-info/licenses/LICENSE
cogent3_h5seqs-0.7.1.dist-info/RECORD
