Metadata-Version: 2.4
Name: cogent3-h5seqs
Version: 0.7.1
Summary: HDF5 storage driver for cogent3 sequence collections
Project-URL: Bug Tracker, https://github.com/cogent3/cogent3-h5seqs/issues
Project-URL: Source Code, https://github.com/cogent3/cogent3-h5seqs
Author-email: Gavin Huttley <Gavin.Huttley@anu.edu.au>
License: BSD 3-Clause License
License-File: LICENSE
Keywords: bioinformatics,biology,evolution,genomics,phylogeny,statistics
Classifier: Development Status :: 3 - Alpha
Classifier: Intended Audience :: Science/Research
Classifier: License :: OSI Approved :: BSD License
Classifier: Operating System :: OS Independent
Classifier: Programming Language :: Python :: 3.11
Classifier: Programming Language :: Python :: 3.12
Classifier: Programming Language :: Python :: 3.13
Classifier: Topic :: Scientific/Engineering :: Bio-Informatics
Classifier: Topic :: Software Development :: Libraries :: Python Modules
Requires-Python: <3.14,>=3.11
Requires-Dist: cogent3>=2025.9.8a2
Requires-Dist: h5py>=3.13.0
Requires-Dist: numpy>=2.2.4
Requires-Dist: typing-extensions>=4.13.2
Requires-Dist: xxhash
Provides-Extra: dev
Requires-Dist: nox>=2025.2.9; extra == 'dev'
Requires-Dist: pytest-cov>=6.1.1; extra == 'dev'
Requires-Dist: pytest>=8.3.5; extra == 'dev'
Requires-Dist: ruff>=0.12.9; extra == 'dev'
